curious_slido/__init__.py
curious_slido/slido_client.py
curious_slido-0.1.0.dist-info/WHEEL
curious_slido-0.1.0.dist-info/METADATA
curious_slido-0.1.0.dist-info/RECORD
