Metadata-Version: 2.1
Name: curious-slido
Version: 0.1.0
Summary: Sends question to a sli.do event
Home-page: https://github.com/b0g3r/curious-slido
License: MIT
Keywords: slido,sli.do
Author: Dima Boger
Author-email: kotvberloge@gmail.com
Requires-Python: >=3.7,<4.0
Classifier: License :: OSI Approved :: MIT License
Classifier: Programming Language :: Python :: 3
Classifier: Programming Language :: Python :: 3.7
Classifier: Programming Language :: Python :: 3.8
Requires-Dist: requests (>=2.23.0,<3.0.0)
Project-URL: Repository, https://github.com/b0g3r/curious-slido
